Workbook

Sheet - AYUDA -
B4: Ayuda

Sheet Precios 
B5: Comparación de Precios entre diferentes proveedores
B6: Ingresa en la tabla los productos, los proveedores y sus precios
J7: ESTADÍSTICAS POR PRODUCTO
B8: PRODUCTO | C8: CANTIDAD | D8: Falabella | E8: Alkosto | F8: Mercado Libre | G8: PROVEEDOR 4 | H8: PROVEEDOR 5 | I8: PROVEEDOR 6 | J8: PRECIO MÁS BAJO | K8: PRECIO PROMEDIO | L8: PRECIO MÁS ALTO
B9: Thermaltake View 270 Plus TG ARGB | C9: 4 | D9: 599000 | E9: 320000 | F9: 169480 | J9: =MIN('Precios '!$D9:$I9) -> 169480 | K9: =IFERROR(AVERAGE('Precios '!$D9:$I9),0) -> 362826.67 | L9: =MAX('Precios '!$D9:$I9) -> 599000
B10: Monitor LG 24 Gamer Ultragear Fhd 180hz Color Black | C10: 8 | D10: 538485 | E10: 409990 | F10: 493900 | J10: =MIN('Precios '!$D10:$I10) -> 409990 | K10: =IFERROR(AVERAGE('Precios '!$D10:$I10),0) -> 480791.67 | L10: =MAX('Precios '!$D10:$I10) -> 538485
B11: Kingston NVMe M.2 SSD | C11: 4 | D11: 360905 | E11: 649900 | F11: 494300 | J11: =MIN('Precios '!$D11:$I11) -> 360905 | K11: =IFERROR(AVERAGE('Precios '!$D11:$I11),0) -> 501701.67 | L11: =MAX('Precios '!$D11:$I11) -> 649900
B12: WD Blue 1 TB (3.5″) HDD | C12: 4 | D12: 688000 | E12: 495000 | F12: 168900 | J12: =MIN('Precios '!$D12:$I12) -> 168900 | K12: =IFERROR(AVERAGE('Precios '!$D12:$I12),0) -> 450633.33 | L12: =MAX('Precios '!$D12:$I12) -> 688000
B13: Poweredge T150 - Tower Server/ Intel Xeon E-2336g/16gb/2tb | C13: 4 | D13: 1199999 | E13: 1199999 | F13: 8400000 | J13: =MIN('Precios '!$D13:$I13) -> 1199999 | K13: =IFERROR(AVERAGE('Precios '!$D13:$I13),0) -> 3599999.3 | L13: =MAX('Precios '!$D13:$I13) -> 8400000
B14: MEMORIA RAM DDR4 16G 3200 CORSAIR VENGEANCE RGB RS | C14: 4 | D14: 260000 | E14: 180039 | F14: 474900 | J14: =MIN('Precios '!$D14:$I14) -> 180039 | K14: =IFERROR(AVERAGE('Precios '!$D14:$I14),0) -> 304979.67 | L14: =MAX('Precios '!$D14:$I14) -> 474900
B15: Combo Dell Wireless Km3322w Teclado + Mouse | C15: 4 | D15: 219900 | E15: 59900 | F15: 84888 | J15: =MIN('Precios '!$D15:$I15) -> 59900 | K15: =IFERROR(AVERAGE('Precios '!$D15:$I15),0) -> 121562.67 | L15: =MAX('Precios '!$D15:$I15) -> 219900
B16: Mouse LENOVO Alámbrico Gaming M210 Negro | C16: 4 | D16: 145900 | E16: 89900 | F16: 145900 | J16: =MIN('Precios '!$D16:$I16) -> 89900 | K16: =IFERROR(AVERAGE('Precios '!$D16:$I16),0) -> 127233.33 | L16: =MAX('Precios '!$D16:$I16) -> 145900
B17: Microsoft Windows 11 Profesional GGK Kit de Legalización 64 Bits Oem 4YR-00229 | C17: 4 | D17: 890000 | E17: 460000 | F17: 640000 | J17: =MIN('Precios '!$D17:$I17) -> 460000 | K17: =IFERROR(AVERAGE('Precios '!$D17:$I17),0) -> 663333.33 | L17: =MAX('Precios '!$D17:$I17) -> 890000
B18: " Suscripción a Visual Studio Enterprise (nuevo)" | C18: 4 | D18: 778741 | E18: 778741 | F18: 5445000 | J18: =MIN('Precios '!$D18:$I18) -> 778741 | K18: =IFERROR(AVERAGE('Precios '!$D18:$I18),0) -> 2334160.7 | L18: =MAX('Precios '!$D18:$I18) -> 5445000
B19: "Licencia Windows 11 Pro ESD Vitalicia " | C19: 4 | D19: 1999990 | E19: 901000 | F19: 824990 | J19: =MIN('Precios '!$D19:$I19) -> 824990 | K19: =IFERROR(AVERAGE('Precios '!$D19:$I19),0) -> 1241993.3 | L19: =MAX('Precios '!$D19:$I19) -> 1999990
B20: SQL Server 2022 Standard (8 cores) | C20: 4 | D20: 1365000 | E20: 1293600 | F20: 3756303 | J20: =MIN('Precios '!$D20:$I20) -> 1293600 | K20: =IFERROR(AVERAGE('Precios '!$D20:$I20),0) -> 2138301 | L20: =MAX('Precios '!$D20:$I20) -> 3756303
B21: Total | D21: =ROUND(SUMPRODUCT('Precios '!$C$9:$C$20,'Precios '!$D$9:$D$20),2) -> 38337620 | E21: =ROUND(SUMPRODUCT('Precios '!$C$9:$C$20,'Precios '!$E$9:$E$20),2) -> 28992236 | F21: =ROUND(SUMPRODUCT('Precios '!$C$9:$C$20,'Precios '!$F$9:$F$20),2) -> 86369844 | G21: =ROUND(SUMPRODUCT('Precios '!$C$9:$C$20,'Precios '!$G$9:$G$20),2) -> 0 | H21: =ROUND(SUMPRODUCT('Precios '!$C$9:$C$20,'Precios '!$H$9:$H$20),2) -> 0 | I21: =ROUND(SUMPRODUCT('Precios '!$C$9:$C$20,'Precios '!$I$9:$I$20),2) -> 0
B24: DATOS ADICIONALES
B25: TIEMPO DE ENTREGA (DÍAS) | D25: Horas de dia los 7 dias de la semana | E25: de 3 a 5 minutos | F25: 3 a 10 dias habiles | G25: entrega de 2 dias habiles | H25: 1 a 5 dias habiles | I25: 5 dias laborales
B26: COSTO DE ENVÍO | D26: 0 | E26: $ 7.055 | F26: $287.497 | G26: 0 | H26: $295.39 | I26: 0
B27: FORMAS DE PAGO
D29: contado | E29: contado | F29: contado | G29: contado | H29: contado | I29: contado

Sheet Soporte
B7: Almendras | C7: 1 | D7: 498 | E7: 420 | F7: 450 | G7: 230 | H7: 600 | I7: 520
B8: Nueces | C8: 2 | D8: 450 | E8: 220 | F8: 405 | G8: 495 | H8: 540 | I8: 200
B9: Pistachos | C9: 2 | D9: 650 | E9: 620 | F9: 666 | G9: 400 | H9: 648 | I9: 452.4
B10: Pecán | C10: 1 | D10: 585 | E10: 558 | F10: 320 | G10: 360 | H10: 583.2 | I10: 407.16
B11: Bananas | C11: 3 | D11: 526.5 | E11: 502.2 | F11: 539.46 | G11: 300 | H11: 500 | I11: 366.44
B12: Pasas | C12: 1 | D12: 473.8 | E12: 200 | F12: 485.51 | G12: 291.6 | H12: 270 | I12: 220
D19: 30 | E19: 10 | F19: 15 | G19: 15 | H19: 15 | I19: 10
D20: 10 | E20: 10 | F20: 10 | G20: Gratis | H20: 5 | I20: Gratis
D21: Efvo | E21: Efvo | F21: Mercado Pago | G21: Efectivo | H21: Mercado Pago | I21: Mercado Pago
D22: Tarjeta | E22: Tarjeta | F22: Tarjeta cuotas | G22: Mercado Pago | H22: Tarjeta cuotas | I22: Tarjeta cuotas
B28: Piñones | C28: 1 | D28: 340 | E28: 330 | F28: 440 | G28: 400 | H28: 320 | I28: 330
B29: Cranberries | C29: 1 | D29: 220 | E29: 230 | F29: 240 | G29: 220 | H29: 219 | I29: 218
B30: Castañas | C30: 2 | D30: 560 | E30: 580 | F30: 550 | G30: 520 | H30: 551 | I30: 550
B35: China Co
B36: 250
B37: 440
B38: 440
B39: 350
B40: 420
B41: 199
